[{"name": "Advanced Course on EMI & AC", "uid": "5PE23WI5", "author_username": "nitinsachan.iitm-2544"}, {"name": "Emerge: Complete Course on IUPAC Nomenclature", "uid": "77DPCLVM", "author_username": "kcf521"}, {"name": "Revision Course on Organic Chemistry for Class 12 - IIT JEE", "uid": "V0VC3S69", "author_username": "sk2003"}, {"name": "Course on Aromaticity and Reaction Mechanisms - Class 11", "uid": "Y2CVVMRP", "author_username": "kcf521"}, {"name": "Course on Physics for INPHO Foundation & JEE Advance 2023", "uid": "SC5SCBW4", "author_username": "nitinsachan.iitm-2544"}, {"name": "Emerge: Course on Organic Molecules & Degree of Unsaturation", "uid": "HS4UXV8I", "author_username": "kcf521"}, {"name": "Ultimate Practice Course on Mathematics for JEE 2022", "uid": "VUCKQ3B7", "author_username": "vineetloomba"}, {"name": "Top 250 Problems for IIT JEE 2023 (April)", "uid": "OGE48X5J", "author_username": "vineetloomba"}, {"name": "Course on P-Block Group 16", "uid": "EB0OAV8C", "author_username": "PMSsir"}, {"name": "Detailed Course on Straight Lines and Circles - JEE Mains and Advanced", "uid": "C351MWOE", "author_username": "vineetloomba"}, {"name": "Evolve: Course on P-block (Group 13, 14)", "uid": "C88X5ICK", "author_username": "PMSsir"}, {"name": "Excel Course on Permutations Combinations, Binomial Theorem & Probability", "uid": "ODJNZYSV", "author_username": "vineetloomba"}, {"name": "Emerge: Detailed Course on Isomerism (Structural and Stereo)", "uid": "ARLF8ZKB", "author_username": "kcf521"}, {"name": "Advance Course on Current Electricity and Capacitors", "uid": "5I6E44QH", "author_username": "nitinsachan.iitm-2544"}, {"name": "Advanced Course on Modern Physics", "uid": "C7AABCGY", "author_username": "nitinsachan.iitm-2544"}, {"name": "Course on Physics for INPHO Foundation & JEE Advanced 2023", "uid": "DI70N9OY", "author_username": "nitinsachan.iitm-2544"}, {"name": "Course on Metallurgy for Class 12", "uid": "D4S1XP1F", "author_username": "PMSsir"}, {"name": "Excel: Course on Tautomerism & Esters Hydrolysis Mechanism", "uid": "P2TKDS9Q", "author_username": "kcf521"}, {"name": "Course on Physics for INPHO Foundation and JEE Advance 2023 (LOM)", "uid": "VSY2P519", "author_username": "nitinsachan.iitm-2544"}, {"name": "Course on GOC: Acids, Bases, and ABR (Basic to Advance)", "uid": "MNOHNJZ4", "author_username": "kcf521"}, {"name": "INPHO Foundation: Advance Course on Magnetics", "uid": "78TE62LG", "author_username": "nitinsachan.iitm-2544"}, {"name": "Course on Environmental Chemistry for IIT JEE", "uid": "2QALIDZY", "author_username": "PMSsir"}, {"name": "Detailed Course on Limits, Continuity & Differentiability for JEE 2024", "uid": "9FYJ5RA4", "author_username": "vineetloomba"}, {"name": "Excel: Course on Trigonometry for JEE 2024", "uid": "POPY119T", "author_username": "vineetloomba"}, {"name": "Advanced Course on Electrostatics & Capacitors for JEE 2022 & 2023", "uid": "UU9IREWE", "author_username": "nitinsachan.iitm-2544"}, {"name": "Detailed Course on Vector & 3D Geometry", "uid": "K477THE5", "author_username": "vineetloomba"}, {"name": "Advance Course of Surface Tension, Viscosity & Elasticity", "uid": "ZLWF1K8M", "author_username": "nitinsachan.iitm-2544"}, {"name": "Course on S-Block, Hydrogen & its Compounds - IIT JEE", "uid": "IBP1Z76R", "author_username": "PMSsir"}, {"name": "Champs: Course on Organic Chemistry for JEE Mains & Advance 2022", "uid": "8QH6WLJG", "author_username": "ashishbaba.mishra624"}, {"name": "INPHO: Advance Course on Thermodynamics", "uid": "3KAY77PA", "author_username": "nitinsachan.iitm-2544"}, {"name": "Course on Isolation of Metals", "uid": "BLK0OOJD", "author_username": "PMSsir"}, {"name": "INPHO: Course on Centre of Mass & Conservation of Linear Momentum for JEE 2023", "uid": "0FECWPVK", "author_username": "nitinsachan.iitm-2544"}, {"name": "Evolve: Course on D and F Block - IIT JEE", "uid": "0Y3K0AVQ", "author_username": "PMSsir"}, {"name": "Course on GOC: Basic to Advance - IIT JEE", "uid": "IXRUHMOK", "author_username": "kcf521"}, {"name": "Theory Course on Matrices & Determinants - IIT JEE, 2023", "uid": "461EDM8U", "author_username": "vineetloomba"}, {"name": "INPHO: Advance Course on Rotational Motion for JEE 2023", "uid": "DN03IHIJ", "author_username": "nitinsachan.iitm-2544"}, {"name": "Class 12: Course on Coordination Compounds", "uid": "S7HZ8DON", "author_username": "PMSsir"}, {"name": "Course on Qualitative Analysis for IIT JEE", "uid": "A112MEWN", "author_username": "PMSsir"}, {"name": "Types of Chemical Reactions", "uid": "D9VV80B6", "author_username": "PMSsir"}, {"name": "Advanced Course on Fluid Mechanics", "uid": "D4ZI1AFB", "author_username": "nitinsachan.iitm-2544"}, {"name": "Course on P-Block Group 15", "uid": "AN34UPCR", "author_username": "PMSsir"}, {"name": "Course on Fundamentals of Calculus for JEE 2024", "uid": "YZQL3T1A", "author_username": "vineetloomba"}, {"name": "INPHO: Advance Course on SHM & Waves", "uid": "XU6V8R4E", "author_username": "nitinsachan.iitm-2544"}, {"name": "Comprehensive Course on Hydrocarbons : IIT-JEE 2024", "uid": "A7TOJ46D", "author_username": "kcf521"}, {"name": "Course on Inorganic Chemistry (Group 17 & 18) for JEE Mains & Advanced", "uid": "LHOFP4ZE", "author_username": "PMSsir"}, {"name": "Emerge : Course on Basic Organic Chemistry (BOC)", "uid": "OG4ZV74I", "author_username": "kcf521"}, {"name": "INPHO: Advance Course on Gravitation", "uid": "FCLNIAGR", "author_username": "nitinsachan.iitm-2544"}, {"name": "Excel Course on Geometrical & Wave Optics for JEE 2023: INPHO Foundation", "uid": "ZR275D98", "author_username": "nitinsachan.iitm-2544"}]